{"url": "https://help.marketplace.virginia.gov/hc/en-us/articles/11972882566029-Health-Reimbursement-Account-HRA-", "scraped_date": "February 02 24", "published_date": "2023-08-11", "question": "Health Reimbursement Account (HRA)", "text": "Health Reimbursement Account (HRA)\n          \n        \nHealth Reimbursement Accounts (HRAs) are employer-funded group health plans from which employees are reimbursed tax-free for qualified medical expenses up to a fixed dollar amount per year. Unused amounts may be rolled over to be used in subsequent years. The employer funds and owns the account. Health Reimbursement Accounts are sometimes called Health Reimbursement Arrangements."}